<annotation>
	<folder>imgs</folder>
	<filename>rim_2018-08-15_05-41-12_18079693_Vin_LF99348.jpg</filename>
	<path>/Users/oezguensi/Code/Other\ Projects/simple-tf-od/data/imgs/rim_2018-08-15_05-41-12_18079693_Vin_LF99348.jpg</path>
	<source>
		<database>Unknown</database>
	</source>
	<size>
		<width>512</width>
		<height>512</height>
		<depth>3</depth>
	</size>
	<segmented>0</segmented>
	<object>
		<name>standard</name>
		<pose>Unspecified</pose>
		<truncated>0</truncated>
		<difficult>0</difficult>
		<bndbox>
			<xmin>305</xmin>
			<ymin>251</ymin>
			<xmax>327</xmax>
			<ymax>273</ymax>
		</bndbox>
	</object>
	<object>
		<name>standard</name>
		<pose>Unspecified</pose>
		<truncated>0</truncated>
		<difficult>0</difficult>
		<bndbox>
			<xmin>215</xmin>
			<ymin>204</ymin>
			<xmax>237</xmax>
			<ymax>226</ymax>
		</bndbox>
	</object>
	<object>
		<name>standard</name>
		<pose>Unspecified</pose>
		<truncated>0</truncated>
		<difficult>0</difficult>
		<bndbox>
			<xmin>260</xmin>
			<ymin>294</ymin>
			<xmax>282</xmax>
			<ymax>316</ymax>
		</bndbox>
	</object>
	<object>
		<name>standard</name>
		<pose>Unspecified</pose>
		<truncated>0</truncated>
		<difficult>0</difficult>
		<bndbox>
			<xmin>205</xmin>
			<ymin>266</ymin>
			<xmax>227</xmax>
			<ymax>288</ymax>
		</bndbox>
	</object>
	<object>
		<name>security</name>
		<pose>Unspecified</pose>
		<truncated>0</truncated>
		<difficult>0</difficult>
		<bndbox>
			<xmin>274</xmin>
			<ymin>193</ymin>
			<xmax>297</xmax>
			<ymax>217</ymax>
		</bndbox>
	</object>
</annotation>
